setup.py
isoprene_pumpjack/__init__.py
isoprene_pumpjack/api.py
isoprene_pumpjack/wsgi.py
isoprene_pumpjack.egg-info/PKG-INFO
isoprene_pumpjack.egg-info/SOURCES.txt
isoprene_pumpjack.egg-info/dependency_links.txt
isoprene_pumpjack.egg-info/entry_points.txt
isoprene_pumpjack.egg-info/not-zip-safe
isoprene_pumpjack.egg-info/requires.txt
isoprene_pumpjack.egg-info/top_level.txt
isoprene_pumpjack/constants/__init__.py
isoprene_pumpjack/constants/environment.py
isoprene_pumpjack/exceptions/__init__.py
isoprene_pumpjack/helpers/__init__.py
isoprene_pumpjack/helpers/services.py
isoprene_pumpjack/resources/__init__.py
isoprene_pumpjack/resources/dev.py
isoprene_pumpjack/resources/discovery.py
isoprene_pumpjack/resources/explore.py
isoprene_pumpjack/resources/graphs.py
isoprene_pumpjack/resources/search.py
isoprene_pumpjack/resources/synaptic_scout_config.py
isoprene_pumpjack/utils/__init__.py
isoprene_pumpjack/utils/dolphins.py
isoprene_pumpjack/utils/neo_to_d3.py
tests/utils/__init__.py
tests/utils/test_neo_to_d3.py