Metadata-Version: 1.1
Name: isoprene-pumpjack
Version: 0.0.5
Summary: Backend for synaptic-scout; request data from Neo4j, perform searches in Elastic, and pump data between the two.
Home-page: https://github.com/tommilligan/isoprene-pumpjack/
Author: Tom Milligan
Author-email: code@tommilligan.net
License: Apache License 2.0
Keywords: neo neo4j elastic elasticsearch graph iterative
Platform: any
Classifier: Programming Language :: Python :: 2
Classifier: Programming Language :: Python :: 2.7
Classifier: License :: OSI Approved :: Apache Software License
